<?xml version="1.0" encoding="UTF-8" ?>
<odoo>
    <record id="sale_form_view" model="ir.ui.view">
        <field name="name">sale.order.form.inherit</field>
        <field name="model">sale.order</field>
        <field name="inherit_id" ref="sale.view_order_form" />
        <field name="arch" type="xml">
            <!-- <xpath expr="//div[@name='button_box']" position="inside">
                <button type="object" name="action_view_request" class="oe_stat_button" icon="fa-object-group" groups="podiatry_clinical_request_group.group_podiatry_request_group_list" attrs="{'readonly':[('is_editable', '=', False)]}" context="{'model_name': 'podiatry.request.group'}">
                    <field name="request_group_count" widget="statinfo" string="Request Groups" />
                    <field name='request_group_ids' invisible="1" />
                </button>
            </xpath> -->

            <field name="sale_order_template_id" position="before">
                <field name="customer_contact_id" context="{'default_parent_id': partner_id, 'default_type': 'contact', 'default_is_company': False, 'default_company_type': 'person'}" />
            </field>
        </field>
    </record>
</odoo>
